MANIFEST.in
README.rst
setup.cfg
setup.py
makeyfile/__init__.py
makeyfile/command.py
makeyfile/contextmanagers.py
makeyfile/discovery.py
makeyfile/exceptions.py
makeyfile/loader.py
makeyfile/makeyfile.commands.json
makeyfile/makeyfile.py
makeyfile/register.py
makeyfile/resolver.py
makeyfile/runner.py
makeyfile.egg-info/PKG-INFO
makeyfile.egg-info/SOURCES.txt
makeyfile.egg-info/dependency_links.txt
makeyfile.egg-info/entry_points.txt
makeyfile.egg-info/requires.txt
makeyfile.egg-info/top_level.txt
makeyfile/commands/__init__.py
makeyfile/commands/base.py
makeyfile/commands/dump.py
makeyfile/commands/list.py
makeyfile/runners/__init__.py
makeyfile/runners/base.py
makeyfile/runners/command.py
makeyfile/runners/py.py
makeyfile/runners/sequence.py
makeyfile/runners/shell.py